{
    "version": "1.105.0",
    "description": "vscode - 一个轻量级、功能强大，插件生态丰富的文件编辑器 | vscode - A lightweight but powerful source code editor.",
    "homepage": "https://code.visualstudio.com/",
    "license": {
        "identifier": "Microsoft Software License",
        "url": "https://code.visualstudio.com/License/"
    },
    "architecture": {
        "64bit": {
            "url": "https://vscode.download.prss.microsoft.com/dbazure/download/stable/03c265b1adee71ac88f833e065f7bb956b60550a/vscode_cli_win32_x64_cli.zip",
            "hash": "632f0180bc0cc306c3adfa96131612405ad28d9dee6970c5093fba6302b782c8"
        },
        "arm64": {
            "url": "https://vscode.download.prss.microsoft.com/dbazure/download/stable/03c265b1adee71ac88f833e065f7bb956b60550a/vscode_cli_win32_arm64_cli.zip",
            "hash": "af36d88f3530d6ca9c3b830c09c6f7cc43f3aeca40fbcb2aba9f389034d392e3"
        }
    },
    "bin": "code.exe",
    "pre_install": [
        "$bucket = if ($bucket) { $bucket } else { (scoop config).'abgox-abyss-bucket-name' }",
        ". \"$bucketsdir\\$bucket\\bin\\utils.ps1\"",
        "A-Start-Install",
        "# A-New-LinkDirectory @(\"$env:AppData\\xxx\")"
    ],
    "post_install": [
        "$bucket = if ($bucket) { $bucket } else { (scoop config).'abgox-abyss-bucket-name' }",
        ". \"$bucketsdir\\$bucket\\bin\\utils.ps1\"",
        "A-Complete-Install"
    ],
    "pre_uninstall": [
        "$bucket = if ($install.bucket) { $install.bucket } else { (scoop config).'abgox-abyss-bucket-name' }",
        ". \"$bucketsdir\\$bucket\\bin\\utils.ps1\"",
        "A-Start-Uninstall",
        "A-Stop-Process",
        "A-Remove-Link"
    ],
    "post_uninstall": [
        "$bucket = if ($install.bucket) { $install.bucket } else { (scoop config).'abgox-abyss-bucket-name' }",
        ". \"$bucketsdir\\$bucket\\bin\\utils.ps1\"",
        "A-Complete-Uninstall"
    ],
    "checkver": {
        "script": [
            ". \"$pwd\\bin\\utils.ps1\"",
            "$InstallerInfo = A-Get-InstallerInfoFromWinget 'Microsoft.VisualStudioCode.CLI' 'zip'",
            "\"ver:$($InstallerInfo.PackageVersion);\"",
            "\"x64:$($InstallerInfo.x64_machine.InstallerUrl);\"",
            "\"x86:$($InstallerInfo.x86_machine.InstallerUrl);\"",
            "\"arm64:$($InstallerInfo.arm64_machine.InstallerUrl);\""
        ],
        "regex": "ver:(?<version>[^;]+)(?:; x64:(?<x64>[^;]*))?(?:; x86:(?<x86>[^;]*))?(?:; arm64:(?<arm64>[^;]*))?"
    },
    "autoupdate": {
        "architecture": {
            "64bit": {
                "url": "$matchX64",
                "hash": {
                    "url": "bin/scoop-auto-check-update-temp-data.jsonc",
                    "jsonpath": "$.x64_machine.InstallerSha256"
                }
            },
            "arm64": {
                "url": "$matchArm64",
                "hash": {
                    "url": "bin/scoop-auto-check-update-temp-data.jsonc",
                    "jsonpath": "$.arm64_machine.InstallerSha256"
                }
            }
        }
    }
}
