{
    "version": "1.0.35",
    "description": "(Mono: 等宽/连字/全宽破折号, HC: HongKong Chinese, Unhinted: No-FontHinting) 一款 2:1 等宽字体 | (Mono: Monospace/Ligature/Full-width dash, HC: HongKong Chinese, Unhinted: No-FontHinting) 2:1 monospaced font",
    "homepage": "https://github.com/be5invis/Sarasa-Gothic",
    "license": {
        "identifier": "OFL-1.1",
        "url": "https://github.com/be5invis/Sarasa-Gothic/blob/main/LICENSE"
    },
    "fonts": "Sarasa Mono HC",
    "architecture": {
        "64bit": {
            "url": "https://github.com/be5invis/Sarasa-Gothic/releases/download/v1.0.35/SarasaMonoHC-TTF-Unhinted-1.0.35.7z",
            "hash": "efe7acaf3b8abc10ac425aad3f307f7d48b03bfefdbaa9365eca5c04d6a05a9f"
        },
        "arm64": {
            "url": "https://github.com/be5invis/Sarasa-Gothic/releases/download/v1.0.35/SarasaMonoHC-TTF-Unhinted-1.0.35.7z",
            "hash": "efe7acaf3b8abc10ac425aad3f307f7d48b03bfefdbaa9365eca5c04d6a05a9f"
        }
    },
    "pre_install": [
        "$bucket = if ($bucket) { $bucket } else { (scoop config).'abgox-abyss-bucket-name' }",
        ". $bucketsdir\\$bucket\\script\\utils.ps1",
        "A-Start-Install",
        "A-Deny-IfAppConflict 'be5invis.Sarasa.Mono-HC', 'be5invis.Sarasa.Mono-HC-Unhinted'",
        "A-Add-Font"
    ],
    "post_install": [
        "$bucket = if ($bucket) { $bucket } else { (scoop config).'abgox-abyss-bucket-name' }",
        ". $bucketsdir\\$bucket\\script\\utils.ps1",
        "A-Complete-Install"
    ],
    "pre_uninstall": [
        "$bucket = if ($bucket) { $bucket } else { (scoop config).'abgox-abyss-bucket-name' }",
        ". $bucketsdir\\$bucket\\script\\utils.ps1",
        "A-Start-Uninstall"
    ],
    "post_uninstall": [
        "$bucket = if ($bucket) { $bucket } else { (scoop config).'abgox-abyss-bucket-name' }",
        ". $bucketsdir\\$bucket\\script\\utils.ps1",
        "A-Complete-Uninstall"
    ],
    "checkver": {
        "script": [
            ". $pwd\\script\\utils.ps1",
            "A-Get-VersionFromGithubAPI"
        ],
        "regex": "(.+)"
    },
    "autoupdate": {
        "architecture": {
            "64bit": {
                "url": "https://github.com/be5invis/Sarasa-Gothic/releases/download/v$version/SarasaMonoHC-TTF-Unhinted-$version.7z"
            },
            "arm64": {
                "url": "https://github.com/be5invis/Sarasa-Gothic/releases/download/v$version/SarasaMonoHC-TTF-Unhinted-$version.7z"
            }
        },
        "hash": {
            "mode": "github"
        }
    }
}
