{
    "version": "0.25.1",
    "description": "一款注重隐私、本地优先、开源且即用型的 Notion 与 Miro 替代方案 | A privacy-focused, local-first, open-source, and ready-to-use alternative for Notion & Miro.",
    "homepage": "https://affine.pro/",
    "license": {
        "identifier": "Unknown",
        "url": "https://github.com/toeverything/AFFiNE/blob/canary/LICENSE"
    },
    "architecture": {
        "64bit": {
            "url": "https://github.com/toeverything/AFFiNE/releases/download/v0.25.1/affine-0.25.1-stable-windows-x64.nsis.exe",
            "hash": "386d5f675beb0b224e0240e2dd5b8552abd8db2ae5ec59435bfeb588f6635aa4"
        },
        "arm64": {
            "url": "https://github.com/toeverything/AFFiNE/releases/download/v0.25.1/affine-0.25.1-stable-windows-arm64.nsis.exe",
            "hash": "4d588aaec881f01ccdba130d8797de5ed42910dd30b75a9b114c920455cb2324"
        }
    },
    "shortcuts": [
        [
            "app\\AFFiNE.exe",
            "AFFiNE"
        ]
    ],
    "pre_install": [
        "$bucket = if ($bucket) { $bucket } else { (scoop config).'abgox-abyss-bucket-name' }",
        ". \"$bucketsdir\\$bucket\\bin\\utils.ps1\"",
        "A-Start-Install",
        "A-New-LinkDirectory @(\"$env:AppData\\AFFiNE\")",
        "A-Install-Exe -Uninstaller 'app\\Uninstall AFFiNE.exe' -ArgumentList @('/CurrentUser','/S',\"/D=$dir\\app\")"
    ],
    "post_install": [
        "$bucket = if ($bucket) { $bucket } else { (scoop config).'abgox-abyss-bucket-name' }",
        ". \"$bucketsdir\\$bucket\\bin\\utils.ps1\"",
        "A-Complete-Install"
    ],
    "pre_uninstall": [
        "$bucket = if ($bucket) { $bucket } else { (scoop config).'abgox-abyss-bucket-name' }",
        ". \"$bucketsdir\\$bucket\\bin\\utils.ps1\"",
        "A-Start-Uninstall",
        "A-Stop-Process",
        "A-Remove-Link",
        "A-Uninstall-Exe",
        "A-Remove-TempData @(\"$env:LocalAppData\\affine-updater\")"
    ],
    "post_uninstall": [
        "$bucket = if ($bucket) { $bucket } else { (scoop config).'abgox-abyss-bucket-name' }",
        ". \"$bucketsdir\\$bucket\\bin\\utils.ps1\"",
        "A-Complete-Uninstall"
    ],
    "checkver": {
        "url": "https://github.com/toeverything/AFFiNE/releases/latest",
        "regex": "href=\"/.+/.+/tree/(?:v|V)?([^\"?]+)"
    },
    "autoupdate": {
        "architecture": {
            "64bit": {
                "url": "https://github.com/toeverything/AFFiNE/releases/download/v$version/affine-$version-stable-windows-x64.nsis.exe"
            },
            "arm64": {
                "url": "https://github.com/toeverything/AFFiNE/releases/download/v$version/affine-$version-stable-windows-arm64.nsis.exe"
            }
        },
        "hash": {
            "mode": "github"
        }
    }
}
