{
    "version": "19.0.1",
    "description": "用于 Qt 框架开发的集成开发环境 (IDE) | IDE for development with the Qt framework",
    "homepage": "https://doc.qt.io/qtcreator/index.html",
    "license": {
        "identifier": "Unknown"
    },
    "architecture": {
        "64bit": {
            "url": "https://github.com/qt-creator/qt-creator/releases/download/v19.0.1/qtcreator-windows-x64-msvc-19.0.1.7z",
            "hash": "d6bc6068587297ce2dc38787bc5ace43368f85ea59520117d2a702d59bd6e40f"
        }
    },
    "extract_to": "app",
    "bin": "app\\bin\\qtcreator.exe",
    "shortcuts": [
        [
            "app\\bin\\qtcreator.exe",
            "Qt Creator"
        ]
    ],
    "link": "$env:AppData\\QtProject",
    "pre_install": [
        "if (!$bucket) { $bucket = (scoop config).'abgox-abyss-bucket-name' }",
        ". $bucketsdir\\$bucket\\util\\1.ps1",
        "A-Start-Install"
    ],
    "post_install": [
        "if (!$bucket) { $bucket = (scoop config).'abgox-abyss-bucket-name' }",
        ". $bucketsdir\\$bucket\\util\\1.ps1",
        "A-Complete-Install"
    ],
    "pre_uninstall": [
        "if (!$bucket) { $bucket = (scoop config).'abgox-abyss-bucket-name' }",
        ". $bucketsdir\\$bucket\\util\\1.ps1",
        "A-Start-Uninstall",
        "A-Stop-Process",
        "A-Remove-Link"
    ],
    "post_uninstall": [
        "if (!$bucket) { $bucket = (scoop config).'abgox-abyss-bucket-name' }",
        ". $bucketsdir\\$bucket\\util\\1.ps1",
        "A-Complete-Uninstall"
    ],
    "checkver": {
        "script": [
            ". $pwd\\util\\1.ps1",
            "A-Get-VersionFromGithubAPI"
        ],
        "regex": "(.+)"
    },
    "autoupdate": {
        "architecture": {
            "64bit": {
                "url": "https://github.com/qt-creator/qt-creator/releases/download/v$version/qtcreator-windows-x64-msvc-$version.7z"
            }
        },
        "hash": {
            "mode": "github"
        }
    }
}
