{
    "version": "0.1.20260109-0.7.1-0.1.20260109",
    "description": "MoonBit 是一种类似 Rust 的语言（支持垃圾回收），也是一个为 WebAssembly 体验优化的工具链。 | MoonBit is a Rust-like language (with GC support) and toolchain optimized for WebAssembly experience.",
    "homepage": "https://www.moonbitlang.com/",
    "license": {
        "identifier": "Apache-2.0,AGPL-3.0-only"
    },
    "architecture": {
        "64bit": {
            "url": [
                "https://cli.moonbitlang.cn/binaries/latest/moonbit-windows-x86_64.zip",
                "https://cli.moonbitlang.cn/cores/core-latest.zip"
            ],
            "hash": [
                "9c19df11c2dbe062f89ae3345aa72afde9bb0652de343645e7b1e3a16f772611",
                "00a9bdcc5e328679f9d7a232e79fc3a27b09e1585eac51a3a411395c3d4f23e8"
            ]
        }
    },
    "extract_to": [
        "app\\.moon",
        "app\\.moon\\lib"
    ],
    "env_set": {
        "MOON_HOME": "$dir\\app\\.moon"
    },
    "env_add_path": "app\\.moon\\bin",
    "persist": [
        [
            "app\\.moon\\registry",
            ".moon\\registry"
        ]
    ],
    "pre_install": [
        "$bucket = if ($bucket) { $bucket } else { (scoop config).'abgox-abyss-bucket-name' }",
        ". $bucketsdir\\$bucket\\script\\utils.ps1",
        "A-Start-Install"
    ],
    "post_install": [
        "$bucket = if ($bucket) { $bucket } else { (scoop config).'abgox-abyss-bucket-name' }",
        ". $bucketsdir\\$bucket\\script\\utils.ps1",
        "Push-Location \"$dir\\app\\.moon\\lib\\core\"",
        "moon.exe bundle --warn-list -a --all --quiet 2>$null",
        "moon.exe bundle --warn-list -a --target wasm-gc --quiet 2>$null",
        "Pop-Location",
        "A-Complete-Install"
    ],
    "pre_uninstall": [
        "$bucket = if ($bucket) { $bucket } else { (scoop config).'abgox-abyss-bucket-name' }",
        ". $bucketsdir\\$bucket\\script\\utils.ps1",
        "A-Start-Uninstall",
        "A-Stop-Process"
    ],
    "post_uninstall": [
        "$bucket = if ($bucket) { $bucket } else { (scoop config).'abgox-abyss-bucket-name' }",
        ". $bucketsdir\\$bucket\\script\\utils.ps1",
        "A-Complete-Uninstall"
    ],
    "checkver": {
        "script": [
            ". $pwd\\script\\utils.ps1",
            "$versionList = @()",
            "Invoke-RestMethod 'https://cli.moonbitlang.com/version.json' | Select-Object -ExpandProperty items | ForEach-Object {",
            "    if ($_.version -match '[\\d.]+') { $versionList += $Matches[0] }",
            "}",
            "$versionList -join '-'"
        ],
        "regex": "(.+)"
    },
    "autoupdate": {
        "architecture": {
            "64bit": {
                "url": [
                    "https://cli.moonbitlang.cn/binaries/latest/moonbit-windows-x86_64.zip",
                    "https://cli.moonbitlang.cn/cores/core-latest.zip"
                ]
            }
        }
    }
}
