{
    "version": "42.13.0",
    "description": "灵活而强大的动态语言 | A flexible and powerful dynamic language",
    "homepage": "https://www.aardio.com/",
    "license": {
        "identifier": "Freeware"
    },
    "architecture": {
        "64bit": {
            "url": "https://www.aardio.com/download/ide/aardio.7z",
            "hash": "dadd3b48ba5ad3c9706acf02b35bc1b6b1ccf29c1af672e00715394b72fff16e"
        }
    },
    "extract_to": "app",
    "shortcuts": [
        [
            "app\\aardio.exe",
            "aardio"
        ]
    ],
    "persist": [
        [
            "app\\config",
            "config"
        ],
        [
            "app\\project",
            "project"
        ]
    ],
    "cleanup": "$env:LocalAppData\\aardio",
    "pre_install": [
        "if (!$bucket) { $bucket = (scoop config).'abgox-abyss-bucket-name' }",
        ". $bucketsdir\\$bucket\\util\\1.ps1",
        "A-Start-Install"
    ],
    "post_install": [
        "if (!$bucket) { $bucket = (scoop config).'abgox-abyss-bucket-name' }",
        ". $bucketsdir\\$bucket\\util\\1.ps1",
        "A-Complete-Install"
    ],
    "pre_uninstall": [
        "if (!$bucket) { $bucket = (scoop config).'abgox-abyss-bucket-name' }",
        ". $bucketsdir\\$bucket\\util\\1.ps1",
        "A-Start-Uninstall",
        "A-Stop-Process"
    ],
    "post_uninstall": [
        "if (!$bucket) { $bucket = (scoop config).'abgox-abyss-bucket-name' }",
        ". $bucketsdir\\$bucket\\util\\1.ps1",
        "A-Complete-Uninstall"
    ],
    "checkver": {
        "url": "https://d.aardio.com/ide/check",
        "jsonpath": "$.version"
    },
    "autoupdate": {
        "architecture": {
            "64bit": {
                "url": "https://www.aardio.com/download/ide/aardio.7z"
            }
        }
    }
}
