{
    "version": "1.87.188",
    "description": "带有广告拦截器的安全、快速且私密的网络浏览器 | Secure, Fast & Private Web Browser with Adblocker",
    "homepage": "https://brave.com/",
    "license": {
        "identifier": "MPL-2.0"
    },
    "architecture": {
        "64bit": {
            "url": "https://github.com/brave/brave-browser/releases/download/v1.87.188/brave-v1.87.188-win32-x64.zip",
            "hash": "cfd1a455ea1d0f6d6a01873ffc98bfcdc80ffe2a931555ff945377cff08fbdd7"
        },
        "arm64": {
            "url": "https://github.com/brave/brave-browser/releases/download/v1.87.188/brave-v1.87.188-win32-arm64.zip",
            "hash": "945d5fc6c6eff2f4c32cdd12a163283fed8c0bd05e9db3e5a16730ad127b555b"
        }
    },
    "extract_to": "app",
    "bin": "app\\brave.exe",
    "shortcuts": [
        [
            "app\\brave.exe",
            "Brave"
        ]
    ],
    "pre_install": [
        "if (!$bucket) { $bucket = (scoop config).'abgox-abyss-bucket-name' }",
        ". $bucketsdir\\$bucket\\script\\utils.ps1",
        "A-Start-Install",
        "A-New-LinkDirectory \"$env:LocalAppData\\BraveSoftware\\Brave-Browser\""
    ],
    "post_install": [
        "if (!$bucket) { $bucket = (scoop config).'abgox-abyss-bucket-name' }",
        ". $bucketsdir\\$bucket\\script\\utils.ps1",
        "A-Complete-Install"
    ],
    "pre_uninstall": [
        "if (!$bucket) { $bucket = (scoop config).'abgox-abyss-bucket-name' }",
        ". $bucketsdir\\$bucket\\script\\utils.ps1",
        "A-Start-Uninstall",
        "A-Stop-Process",
        "A-Remove-Link"
    ],
    "post_uninstall": [
        "if (!$bucket) { $bucket = (scoop config).'abgox-abyss-bucket-name' }",
        ". $bucketsdir\\$bucket\\script\\utils.ps1",
        "A-Complete-Uninstall"
    ],
    "checkver": {
        "script": [
            ". $pwd\\script\\utils.ps1",
            "A-Get-VersionFromGithubAPI"
        ],
        "regex": "(.+)"
    },
    "autoupdate": {
        "architecture": {
            "64bit": {
                "url": "https://github.com/brave/brave-browser/releases/download/v$version/brave-v$version-win32-x64.zip"
            },
            "arm64": {
                "url": "https://github.com/brave/brave-browser/releases/download/v$version/brave-v$version-win32-arm64.zip"
            }
        },
        "hash": {
            "mode": "github"
        }
    }
}
