{
    "version": "4.20",
    "description": "一个可一次性批量重命名多个文件和文件夹的程序 | A program for bulk renaming multiple files and folders at once.",
    "homepage": "https://www.advancedrenamer.com/",
    "license": {
        "identifier": "Unknown",
        "url": "https://www.advancedrenamer.com/license"
    },
    "architecture": {
        "64bit": {
            "url": "https://www.advancedrenamer.com/down/win/advanced_renamer_setup_4_20.exe",
            "hash": "9e863839d5fdad7eaba3be098b370d46bc8f479cdd795efa744d7bb3acc95ae5"
        }
    },
    "extract_to": "app",
    "innosetup": true,
    "bin": "app\\arenc.exe",
    "shortcuts": [
        [
            "app\\ARen.exe",
            "Advanced Renamer"
        ]
    ],
    "pre_install": [
        "$bucket = if ($bucket) { $bucket } else { (scoop config).'abgox-abyss-bucket-name' }",
        ". $bucketsdir\\$bucket\\script\\utils.ps1",
        "A-Start-Install",
        "A-New-LinkDirectory \"$env:AppData\\Hulubulu\\Advanced Renamer $($version.split('.'[0])\")"
    ],
    "post_install": [
        "$bucket = if ($bucket) { $bucket } else { (scoop config).'abgox-abyss-bucket-name' }",
        ". $bucketsdir\\$bucket\\script\\utils.ps1",
        "A-Complete-Install"
    ],
    "pre_uninstall": [
        "$bucket = if ($bucket) { $bucket } else { (scoop config).'abgox-abyss-bucket-name' }",
        ". $bucketsdir\\$bucket\\script\\utils.ps1",
        "A-Start-Uninstall",
        "A-Stop-Process",
        "A-Remove-Link"
    ],
    "post_uninstall": [
        "$bucket = if ($bucket) { $bucket } else { (scoop config).'abgox-abyss-bucket-name' }",
        ". $bucketsdir\\$bucket\\script\\utils.ps1",
        "A-Complete-Uninstall"
    ],
    "checkver": {
        "url": "https://www.advancedrenamer.com/versionlog",
        "regex": "Advanced Renamer\\s+([\\d.]+)\\s"
    },
    "autoupdate": {
        "architecture": {
            "64bit": {
                "url": "https://www.advancedrenamer.com/down/win/advanced_renamer_setup_$underscoreVersion.exe"
            }
        }
    }
}
