{
    "version": "10.18.1",
    "description": "一款快速且节省磁盘空间的 Node 包管理器。A fast and disk space efficient Node package manager.",
    "homepage": "https://pnpm.io/",
    "license": {
        "identifier": "MIT",
        "url": "https://github.com/pnpm/pnpm/blob/main/LICENSE"
    },
    "architecture": {
        "64bit": {
            "url": "https://github.com/pnpm/pnpm/releases/download/v10.18.1/pnpm-win-x64.exe#/pnpm.exe",
            "hash": "a30c43f4a48ea317a5a3ecf8486f27de9e0cfdc2768d4870e23005a3254f3009"
        },
        "arm64": {
            "url": "https://github.com/pnpm/pnpm/releases/download/v10.18.1/pnpm-win-arm64.exe#/pnpm.exe",
            "hash": "ce77420bdf308e1f4ed803b68cd8251c675b9851d6ae1267731e111b40216c51"
        }
    },
    "bin": [
        "pnpm.exe",
        [
            "pnpm.exe",
            "pnpx",
            "dlx"
        ]
    ],
    "pre_install": [
        "$bucket = if ($bucket) { $bucket } else { (scoop config).'abgox-abyss-bucket-name' }",
        ". \"$bucketsdir\\$bucket\\bin\\utils.ps1\"",
        "A-Start-Install",
        "A-New-LinkDirectory @(\"$env:LocalAppData\\pnpm\",\"$env:LocalAppData\\pnpm-state\",\"$env:LocalAppData\\pnpm-cache\")"
    ],
    "post_install": [
        "$bucket = if ($bucket) { $bucket } else { (scoop config).'abgox-abyss-bucket-name' }",
        ". \"$bucketsdir\\$bucket\\bin\\utils.ps1\"",
        "A-Complete-Install"
    ],
    "pre_uninstall": [
        "$bucket = if ($install.bucket) { $install.bucket } else { (scoop config).'abgox-abyss-bucket-name' }",
        ". \"$bucketsdir\\$bucket\\bin\\utils.ps1\"",
        "A-Start-Uninstall",
        "A-Stop-Process",
        "A-Remove-Link"
    ],
    "post_uninstall": [
        "$bucket = if ($install.bucket) { $install.bucket } else { (scoop config).'abgox-abyss-bucket-name' }",
        ". \"$bucketsdir\\$bucket\\bin\\utils.ps1\"",
        "A-Complete-Uninstall"
    ],
    "checkver": {
        "github": "https://github.com/pnpm/pnpm"
    },
    "autoupdate": {
        "architecture": {
            "64bit": {
                "url": "https://github.com/pnpm/pnpm/releases/download/v$version/pnpm-win-x64.exe#/pnpm.exe"
            },
            "arm64": {
                "url": "https://github.com/pnpm/pnpm/releases/download/v$version/pnpm-win-arm64.exe#/pnpm.exe"
            }
        }
    }
}
