{
    "version": "0.4.8",
    "description": "为 fly.io 服务提供的命令行工具 | Command line tools for fly.io services",
    "homepage": "https://fly.io/",
    "license": {
        "identifier": "Apache-2.0"
    },
    "architecture": {
        "64bit": {
            "url": "https://github.com/superfly/flyctl/releases/download/v0.4.8/flyctl_0.4.8_Windows_x86_64.zip",
            "hash": "df48ef333a0dcd7baba6e60c27bcb9bc689facd7c53061cc7544f1c129621afa"
        },
        "arm64": {
            "url": "https://github.com/superfly/flyctl/releases/download/v0.4.8/flyctl_0.4.8_Windows_arm64.zip",
            "hash": "11a49aee11bac312af1cb2e33e8ad266fa650e5c3b2770c29e147510b8dfdbd4"
        }
    },
    "extract_to": "app",
    "bin": [
        "app\\flyctl.exe",
        [
            "app\\flyctl.exe",
            "fly"
        ]
    ],
    "pre_install": [
        "if (!$bucket) { $bucket = (scoop config).'abgox-abyss-bucket-name' }",
        ". $bucketsdir\\$bucket\\script\\utils.ps1",
        "A-Start-Install"
    ],
    "post_install": [
        "if (!$bucket) { $bucket = (scoop config).'abgox-abyss-bucket-name' }",
        ". $bucketsdir\\$bucket\\script\\utils.ps1",
        "A-Complete-Install"
    ],
    "pre_uninstall": [
        "if (!$bucket) { $bucket = (scoop config).'abgox-abyss-bucket-name' }",
        ". $bucketsdir\\$bucket\\script\\utils.ps1",
        "A-Start-Uninstall",
        "A-Stop-Process"
    ],
    "post_uninstall": [
        "if (!$bucket) { $bucket = (scoop config).'abgox-abyss-bucket-name' }",
        ". $bucketsdir\\$bucket\\script\\utils.ps1",
        "A-Complete-Uninstall"
    ],
    "checkver": {
        "script": [
            ". $pwd\\script\\utils.ps1",
            "A-Get-VersionFromGithubAPI"
        ],
        "regex": "(.+)"
    },
    "autoupdate": {
        "architecture": {
            "64bit": {
                "url": "https://github.com/superfly/flyctl/releases/download/v$version/flyctl_$version_Windows_x86_64.zip"
            },
            "arm64": {
                "url": "https://github.com/superfly/flyctl/releases/download/v$version/flyctl_$version_Windows_arm64.zip"
            }
        },
        "hash": {
            "mode": "github"
        }
    }
}
